CHANGES.txt
README.txt
setup.py
xmiparser/__init__.py
xmiparser/interfaces.py
xmiparser/utils.py
xmiparser/xmiparser.py
xmiparser/zargoparser.py
xmiparser.egg-info/PKG-INFO
xmiparser.egg-info/SOURCES.txt
xmiparser.egg-info/dependency_links.txt
xmiparser.egg-info/entry_points.txt
xmiparser.egg-info/namespace_packages.txt
xmiparser.egg-info/not-zip-safe
xmiparser.egg-info/requires.txt
xmiparser.egg-info/top_level.txt
xmiparser/doc/umlsample.zargo
xmiparser/tests/__init__.py
xmiparser/tests/test_doctest.py
xmiparser/tests/xmiparser.txt