Metadata-Version: 1.0
Name: xmiparser
Version: 1.5
Summary: XMI Parser (API for the UML XML representation specified by OMG)
Home-page: http://pypi.python.org/pypi/xmiparser
Author: Philipp Auersperg, Jens Klein
Author-email: dev@bluedynamics.com
License: General Public Licence
Platform: UNKNOWN
Classifier: Programming Language :: Python
Classifier: License :: OSI Approved :: GNU General Public License (GPL)
Classifier: Operating System :: OS Independent
